{
    "activate-tts-label": "පෙළ කථනය සක්‍රීය කරන්න",
    "activity-completed": "සම්පූර්ණයි",
    "activity-to-do": "කළ යුතුයි",
    "answers-submitted": "ඔබගේ පිළිතුරු ඔබගේ ගුරුවරයාට ඉදිරිපත් කර ඇත!",
    "autoplay-label": "ස්වයං වාදනය",
    "character-profile-emoji": "පැතිකඩ ඉමොජි",
    "correct-answer": "විශිෂ්ට වැඩක්! ඔබගේ පිළිතුර නිවැරදියි.",
    "describe-images-label": "රූප විස්තර කරන්න",
    "easy-read-label": "පහසු කියවීම",
    "eli5-aria-label": "AI මට පැහැදිලි කිරීම",
    "eli5-close-label": "පැහැදිලි කිරීම වසන්න",
    "eli5-content-lang": "මට පැහැදිලි කිරීමට ඕනෑම දෙයක් ස්පර්ශ කරන්න.",
    "eli5-label": "මට පැහැදිලි කරන්න",
    "eli5-no-content": "පැහැදිලි කිරීමක් නොමැත.",
    "fill-in-the-blank-correct-answer": "විශිෂ්ට වැඩක්!",
    "fill-in-the-blank-correct-the-answers": "කරුණාකර ඔබගේ පිළිතුරු නිවැරදි කරන්න.",
    "fill-in-the-blank-not-complete": "කරුණාකර සියලුම ක්ෂේත්‍ර පුරවන්න. ${unfilledCount} හිස් ඉතිරියි.",
    "fill-in-the-blank-try-again": "නැවත උත්සාහ කරන්න",
    "filter-terms": "යෙදුම් පෙරන්න...",
    "finish": "අවසන්",
    "glossary-book-label": "පොත් ශබ්දකෝෂය",
    "glossary-highlight-words": "වචන උද්දීපනය කරන්න",
    "glossary-label": "ශබ්දකෝෂය",
    "glossary-no-terms": "ශබ්දකෝෂ යෙදුම් සොයා ගත නොහැක.",
    "glossary-no-terms-filter": "ශබ්දකෝෂ යෙදුම් සොයා ගත නොහැක. සියලුම යෙදුම් බැලීමට පෙරහන ඉවත් කරන්න.",
    "glossary-page-label": "මෙම පිටුවේ",
    "glossary-term-details": "ශබ්දකෝෂ යෙදුම් විස්තර",
    "glossary-view-term": "ශබ්දකෝෂයේ බලන්න",
    "language-label": "භාෂාව",
    "language-name": "සිංහල",
    "matching-correct-answers": "සියලුම පිළිතුරු නිවැරදියි!",
    "matching-correct-answers-count": "ඔබට ${correctCount} නිවැරදි පිළිතුරු ඇත. නැවත උත්සාහ කරන්න.",
    "multiple-choice-correct-answer": "විශිෂ්ට වැඩක්! ඔබගේ පිළිතුර නිවැරදියි.",
    "multiple-choice-try-again": "නැවත උත්සාහ කරන්න",
    "nav-label": "සංචාලන මෙනුව",
    "next": "ඊළඟ",
    "next-activity": "ඊළඟ ක්‍රියාකාරකම",
    "next-audio": "ඊළඟ ශ්‍රව්‍යයට යන්න",
    "next-page": "ඊළඟ පිටුව",
    "notepad-close-label": "සටහන් පොත වසන්න",
    "notepad-label": "සටහන්",
    "notepad-open-label": "සටහන් පොත විවෘත කරන්න",
    "notepad-placeholder": "ඔබගේ සටහන් මෙහි ලියන්න...",
    "notepad-save-button": "සටහන් සුරකින්න",
    "notepad-save-success": "සටහන් සාර්ථකව සුරකින ලදී!",
    "page": "",
    "previous": "පෙර",
    "previous-audio": "පෙර ශ්‍රව්‍යයට යන්න",
    "previous-page": "පෙර පිටුව",
    "read-aloud-speed-fast": "වේගවත්",
    "read-aloud-speed-normal": "සාමාන්‍ය",
    "read-aloud-speed-slow": "මන්දගාමී",
    "read-aloud-speed-very-fast": "ඉතා වේගවත්",
    "reset-text": "යළි පිහිටුවන්න",
    "retry": "නැවත උත්සාහ කරන්න",
    "sidebar-assistant": "සහායක",
    "sidebar-settings": "සැකසීම්",
    "sidebar-title": "ප්‍රවේශ්‍ය මෙනුව",
    "sign-language-label": "සං‍කේත භාෂාව",
    "sign-language-quick-toggle-label": "සං‍කේත භාෂාව ඉක්මන් ටොගල් බොත්තම",
    "sorting-correct-answer": "විශිෂ්ට වැඩක්! ඔබගේ පිළිතුර නිවැරදියි.",
    "sorting-not-complete": "ඉදිරිපත් කිරීමට පෙර සියලුම වචන කාණ්ඩවල තබන්න. (${cardsPlaced}/${totalCards} වචන තබා ඇත)",
    "sorting-results": "ඔබට ${correctCount} නිවැරදි පිළිතුරු සහ ${incorrectCount} වැරදි පිළිතුරු ඇත. නැවත උත්සාහ කරන්නද?",
    "state-label": "ස්වයං-සැඟවුණු මෙනු",
    "submit-text": "ඉදිරිපත් කරන්න",
    "success-try-next-activity": "විශිෂ්ට වැඩක්! ඊළඟ ක්‍රියාකාරකම උත්සාහ කරන්න!",
    "syllable-label": "අක්ෂර",
    "text-read-aloud-speed": "වේගය",
    "toc-title": "අන්තර්ගතය",
    "tts-label": "පෙළ කථනය",
    "tutorial-closed-announcement": "නිබන්ධනය වසා ඇත. ඔබට Alt සහ Shift සහ A භාවිතා කරමින් ප්‍රවේශ්‍ය මෙනුව විවෘත සහ වසා ගත හැකි බව, Alt සහ Shift සහ ඊතල භාවිතා කරමින් පිටු අතර සංචාලනය කළ හැකි බව, සහ Alt සහ Shift සහ X භාවිතා කරමින් සංචාලන මෙනුව විවෘත සහ වසා ගත හැකි බව මතක තබා ගන්න. දකුණු කෙළවරේ බොත්තම භාවිතා කරමින් තවත් ප්‍රවේශ්‍ය විශේෂාංග ප්‍රවේශ කළ හැකිය.",
    "tutorial-completed-announcement": "නිබන්ධනය සම්පූර්ණයි. ඔබට Alt සහ Shift සහ A භාවිතා කරමින් ප්‍රවේශ්‍ය මෙනුව විවෘත සහ වසා ගත හැකි බව, Alt සහ Shift සහ ඊතල භාවිතා කරමින් පිටු අතර සංචාලනය කළ හැකි බව, සහ Alt සහ Shift සහ X භාවිතා කරමින් සංචාලන මෙනුව විවෘත සහ වසා ගත හැකි බව මතක තබා ගන්න.",
    "tutorial-description-content": "ඔබ ආරම්භ කිරීමට පෙර, සංචාලනය කරන්නේ කෙසේද, මෙනුව භාවිතා කරන්නේ කෙසේද සහ ප්‍රයෝජනවත් විශේෂාංග ප්‍රවේශ කරන්නේ කෙසේද යන්න පෙන්වීමට ඉක්මන් සංචාරයක්.<br> මෙය බොහෝ කාලයක් ගතවන්නේ නැත!",
    "tutorial-exit-button-aria-label": "නිබන්ධනය වසා පාඩමට ඉදිරියට යන්න",
    "tutorial-skip": "නිබන්ධනය මඟ හරින්න",
    "tutorial-smart-utility-sidebar-label": "ප්‍රවේශ්‍ය මෙනුව",
    "tutorial-start-button-aria-label": "ප්‍රවේශ්‍ය නිබන්ධනය ආරම්භ කරන්න",
    "tutorial-start-button-content": "අපි යමු! 🚀",
    "tutorial-starting-announcement": "නිබන්ධනය ආරම්භ වේ. පළමු පියවර: සංචාලන මෙනුව භාවිතා කරන්නේ කෙසේද. සංචාලන මෙනුව විවෘත සහ වසා ගැනීමට Alt සහ Shift සහ Z භාවිතා කළ හැකි බව මතක තබා ගන්න.",
    "tutorial-step-1-content": "මෙම බොත්තම හරහා ඔබට පොතේ පරිච්ඡේද සහ අභ්‍යාස වෙත ප්‍රවේශ විය හැකිය.",
    "tutorial-step-2-content": "පොතේ විවිධ පිටු හරහා සංචාලනය කිරීමට ඊතල භාවිතා කරන්න.",
    "tutorial-step-3-content": "ඔබට මෙහිදී ඉගෙනුම් මෙවලම් සක්‍රීය කළ හැකිය:<br><br>🤓 පහසු කියවීම<br>🔊 පෙළ කථනය<br>✋ සං‍කේත භාෂාව<br>🤖 AI පැහැදිලි කිරීම්<br>🔤 ශබ්දකෝෂය",
    "tutorial-step-announcement": "නිබන්ධන පියවර {{currentStep}} වන {{totalSteps}}: {{stepContent}}",
    "tutorial-welcome-announcement": "ප්‍රවේශ්‍ය ආකෘතියෙන් මෙම පොතට සාදරයෙන් පිළිගනිමු. යතුරුපුවරු කෙටිමං ලබා ගත හැකිය: පිටු අතර සංචාලනය කිරීමට Alt සහ Shift සහ ඊතල, ප්‍රවේශ්‍ය මෙනුව විවෘත සහ වසා ගැනීමට Alt සහ Shift සහ A, සංචාලනය විවෘත සහ වසා ගැනීමට Alt සහ Shift සහ X. ලබා ගත හැකි ක්‍රියාකාරකම් පිළිබඳ නිබන්ධනයක් ඔබට මඟ පෙන්වනු ඇත.",
    "tutorial-welcome-content": "එහි නව ප්‍රවේශ්‍ය ආකෘතියෙන්!",
    "tutorial-welcome-emoji-label": "අත් රැළි ඉමොජි",
    "tutorial-welcome-title": "ප්‍රවේශ්‍ය ඩිජිටල් පාඨ්‍ය පොතට සාදරයෙන් පිළිගනිමු",
    "username-label": "පරිශීලක නාමය",
    "validation-inappropriate-language": "නුසුදුසු භාෂාව",
    "validation-check-spelling": "ඔබගේ අක්ෂර වින්‍යාසය පරීක්ෂා කරන්න",
    "validation-write-appropriate": "කරුණාකර සුදුසු භාෂාවෙන් ලියන්න සහ නිසි භාෂාව භාවිතා කරන්න",
    "validation-error": "වලංගු කිරීමේ දෝෂයක්",
    "nav-page-tab-label": "පිටු ලැයිස්තුව"
}
